cloudignite/__init__.py
cloudignite/sdk.py
cloudignite_sdk-1.0.1.dist-info/METADATA
cloudignite_sdk-1.0.1.dist-info/WHEEL
cloudignite_sdk-1.0.1.dist-info/top_level.txt
cloudignite_sdk-1.0.1.dist-info/RECORD
